sas_merge/__init__.py
sas_merge/sas_merge.py
sas_merge-0.2.2.dist-info/LICENSE
sas_merge-0.2.2.dist-info/METADATA
sas_merge-0.2.2.dist-info/WHEEL
sas_merge-0.2.2.dist-info/top_level.txt
sas_merge-0.2.2.dist-info/RECORD
